Metadata-Version: 2.1
Name: django-dprog-jfu
Version: 3.0.0
Summary: A Django Library for jQuery File Upload.
Home-page: http://packages.python.org/jfu
Author: Z. Alem, Philippe Docourt
Author-email: alem@cidola.com
Maintainer: Philippe Docourt
License: BSD License
Keywords: django,jquery file upload,multi-upload
Classifier: Environment :: Web Environment
Classifier: Framework :: Django
Classifier: Intended Audience :: Developers
Classifier: License :: OSI Approved :: BSD License
Classifier: Operating System :: OS Independent
Classifier: Programming Language :: Python
Classifier: Programming Language :: Python :: 3.10
Classifier: Programming Language :: Python :: 3.11
Classifier: Topic :: Internet :: WWW/HTTP
Classifier: Topic :: Internet :: WWW/HTTP :: Dynamic Content
License-File: LICENSE
